pod_on_shutdown/__init__.py
pod_on_shutdown/extension.py
localstack_extension_pod_on_shutdown-0.1.1.dist-info/METADATA
localstack_extension_pod_on_shutdown-0.1.1.dist-info/WHEEL
localstack_extension_pod_on_shutdown-0.1.1.dist-info/entry_points.txt
localstack_extension_pod_on_shutdown-0.1.1.dist-info/top_level.txt
localstack_extension_pod_on_shutdown-0.1.1.dist-info/RECORD
