Metadata-Version: 2.1
Name: localstack-extension-pod-on-shutdown
Version: 0.1.1
Summary: This LocalStack extension will create a cloud pod when LS is shutting down automatically
Home-page: https://github.com/lukqw/pod-on-shutdown
Author: lukqw
Author-email: lukas@localstack.cloud
Requires-Dist: localstack-sdk-python
Provides-Extra: dev
Requires-Dist: localstack-core >=1.0 ; extra == 'dev'
